{
	"frames": [
		{
			"duration": 20,
			"hitbox": null,
			"hurtbox": {
				"bottom": 15,
				"left": 0,
				"right": 7,
				"top": 0,
				"type": "animation_hurtbox"
			},
			"sprites": [],
			"type": "animation_frame"
		},
		{
			"duration": 5,
			"hitbox": null,
			"hurtbox": {
				"bottom": 15,
				"left": 0,
				"right": 7,
				"top": 0,
				"type": "animation_hurtbox"
			},
			"sprites": [
				{
					"attr": 1,
					"foreground": false,
					"tile": "TILE_PORTAL",
					"type": "animation_sprite",
					"x": -7,
					"y": 0
				},
				{
					"attr": 193,
					"foreground": false,
					"tile": "TILE_PORTAL",
					"type": "animation_sprite",
					"x": 1,
					"y": 0
				}
			],
			"type": "animation_frame"
		},
		{
			"duration": 10,
			"hitbox": null,
			"hurtbox": {
				"bottom": 15,
				"left": 0,
				"right": 7,
				"top": 0,
				"type": "animation_hurtbox"
			},
			"sprites": [
				{
					"attr": 1,
					"foreground": false,
					"tile": "TILE_PORTAL",
					"type": "animation_sprite",
					"x": -7,
					"y": -8
				},
				{
					"attr": 193,
					"foreground": false,
					"tile": "TILE_PORTAL",
					"type": "animation_sprite",
					"x": 1,
					"y": -8
				},
				{
					"attr": 129,
					"foreground": false,
					"tile": "TILE_PORTAL",
					"type": "animation_sprite",
					"x": -7,
					"y": 0
				},
				{
					"attr": 65,
					"foreground": false,
					"tile": "TILE_PORTAL",
					"type": "animation_sprite",
					"x": 1,
					"y": 0
				},
				{
					"attr": 1,
					"foreground": false,
					"tile": "TILE_PORTAL",
					"type": "animation_sprite",
					"x": -7,
					"y": 8
				},
				{
					"attr": 193,
					"foreground": false,
					"tile": "TILE_PORTAL",
					"type": "animation_sprite",
					"x": 1,
					"y": 8
				}
			],
			"type": "animation_frame"
		},
		{
			"duration": 5,
			"hitbox": null,
			"hurtbox": {
				"bottom": 15,
				"left": 0,
				"right": 7,
				"top": 0,
				"type": "animation_hurtbox"
			},
			"sprites": [
				{
					"attr": 129,
					"foreground": true,
					"tile": "TILE_VERTICAL_SCIMITAR_HANDLE",
					"type": "animation_sprite",
					"x": -7,
					"y": 8
				},
				{
					"attr": 0,
					"foreground": true,
					"tile": "TILE_IDLE_SINBAD_HEAD",
					"type": "animation_sprite",
					"x": 0,
					"y": 0
				},
				{
					"attr": 0,
					"foreground": true,
					"tile": "TILE_IDLE_SINBAD_BODY",
					"type": "animation_sprite",
					"x": 0,
					"y": 8
				},
				{
					"attr": 129,
					"foreground": false,
					"tile": "TILE_PORTAL",
					"type": "animation_sprite",
					"x": -7,
					"y": -8
				},
				{
					"attr": 65,
					"foreground": false,
					"tile": "TILE_PORTAL",
					"type": "animation_sprite",
					"x": 1,
					"y": -8
				},
				{
					"attr": 1,
					"foreground": false,
					"tile": "TILE_PORTAL",
					"type": "animation_sprite",
					"x": -7,
					"y": 0
				},
				{
					"attr": 193,
					"foreground": false,
					"tile": "TILE_PORTAL",
					"type": "animation_sprite",
					"x": 1,
					"y": 0
				},
				{
					"attr": 129,
					"foreground": false,
					"tile": "TILE_PORTAL",
					"type": "animation_sprite",
					"x": -7,
					"y": 8
				},
				{
					"attr": 65,
					"foreground": false,
					"tile": "TILE_PORTAL",
					"type": "animation_sprite",
					"x": 1,
					"y": 8
				}
			],
			"type": "animation_frame"
		},
		{
			"duration": 5,
			"hitbox": null,
			"hurtbox": {
				"bottom": 15,
				"left": 0,
				"right": 7,
				"top": 0,
				"type": "animation_hurtbox"
			},
			"sprites": [
				{
					"attr": 129,
					"foreground": true,
					"tile": "TILE_VERTICAL_SCIMITAR_HANDLE",
					"type": "animation_sprite",
					"x": -7,
					"y": 8
				},
				{
					"attr": 0,
					"foreground": true,
					"tile": "TILE_SIDE_TILT_SINBAD_3_1",
					"type": "animation_sprite",
					"x": -8,
					"y": 0
				},
				{
					"attr": 0,
					"foreground": true,
					"tile": "TILE_SIDE_TILT_SINBAD_3_2",
					"type": "animation_sprite",
					"x": 0,
					"y": 0
				},
				{
					"attr": 0,
					"foreground": true,
					"tile": "TILE_SIDE_TILT_SINBAD_3_3",
					"type": "animation_sprite",
					"x": 0,
					"y": 8
				},
				{
					"attr": 129,
					"foreground": false,
					"tile": "TILE_PORTAL",
					"type": "animation_sprite",
					"x": -7,
					"y": 0
				},
				{
					"attr": 65,
					"foreground": false,
					"tile": "TILE_PORTAL",
					"type": "animation_sprite",
					"x": 1,
					"y": 0
				}
			],
			"type": "animation_frame"
		},
		{
			"duration": 5,
			"hitbox": null,
			"hurtbox": {
				"bottom": 15,
				"left": 0,
				"right": 7,
				"top": 0,
				"type": "animation_hurtbox"
			},
			"sprites": [
				{
					"attr": 1,
					"foreground": false,
					"tile": "TILE_SCIMITAR_BLADE",
					"type": "animation_sprite",
					"x": -8,
					"y": 6
				},
				{
					"attr": 1,
					"foreground": false,
					"tile": "TILE_SCIMITAR_HANDLE",
					"type": "animation_sprite",
					"x": 0,
					"y": 6
				},
				{
					"attr": 0,
					"foreground": false,
					"tile": "TILE_SIDE_TILT_SINBAD_3_1",
					"type": "animation_sprite",
					"x": -8,
					"y": 0
				},
				{
					"attr": 0,
					"foreground": false,
					"tile": "TILE_SIDE_TILT_SINBAD_3_2",
					"type": "animation_sprite",
					"x": 0,
					"y": 0
				},
				{
					"attr": 0,
					"foreground": false,
					"tile": "TILE_SIDE_TILT_SINBAD_3_3",
					"type": "animation_sprite",
					"x": 0,
					"y": 8
				}
			],
			"type": "animation_frame"
		}
	],
	"name": "anim_sinbad_spawn",
	"type": "animation"
}
